{
  "Afghanistan": ["Kabul", "Kandahar", "Herat", "Mazar-i-Sharif", "Jalalabad"],
  "Albania": ["Tirana", "Durrës", "Vlorë", "Shkodër", "Fier"],
  "Algeria": ["Algiers", "Oran", "Constantine", "Annaba", "Blida"],
  "Argentina": ["Buenos Aires", "Córdoba", "Rosario", "Mendoza", "La Plata", "San Miguel de Tucumán", "Mar del Plata", "Salta", "Santa Fe", "San Juan"],
  "Armenia": ["Yerevan", "Gyumri", "Vanadzor", "Vagharshapat", "Hrazdan"],
  "Australia": ["Sydney", "Melbourne", "Brisbane", "Perth", "Adelaide", "Gold Coast", "Newcastle", "Canberra", "Sunshine Coast", "Wollongong"],
  "Austria": ["Vienna", "Graz", "Linz", "Salzburg", "Innsbruck"],
  "Azerbaijan": ["Baku", "Ganja", "Sumqayit", "Mingachevir", "Qabalah"],
  "Bahrain": ["Manama", "Riffa", "Muharraq", "Hamad Town", "A'ali"],
  "Bangladesh": ["Dhaka", "Chittagong", "Khulna", "Rajshahi", "Sylhet"],
  "Belarus": ["Minsk", "Gomel", "Mogilev", "Vitebsk", "Grodno"],
  "Belgium": ["Brussels", "Antwerp", "Ghent", "Charleroi", "Liège"],
  "Bolivia": ["La Paz", "Santa Cruz", "Cochabamba", "Sucre", "Oruro"],
  "Bosnia and Herzegovina": ["Sarajevo", "Banja Luka", "Tuzla", "Zenica", "Mostar"],
  "Brazil": ["São Paulo", "Rio de Janeiro", "Brasília", "Salvador", "Fortaleza", "Belo Horizonte", "Manaus", "Curitiba", "Recife", "Goiânia"],
  "Bulgaria": ["Sofia", "Plovdiv", "Varna", "Burgas", "Ruse"],
  "Cambodia": ["Phnom Penh", "Siem Reap", "Battambang", "Sihanoukville", "Poipet"],
  "Canada": ["Toronto", "Montreal", "Vancouver", "Calgary", "Edmonton", "Ottawa", "Winnipeg", "Quebec City", "Hamilton", "Kitchener"],
  "Chile": ["Santiago", "Valparaíso", "Concepción", "La Serena", "Antofagasta", "Temuco", "Rancagua", "Talca", "Arica", "Chillán"],
  "China": ["Beijing", "Shanghai", "Guangzhou", "Shenzhen", "Tianjin", "Wuhan", "Dongguan", "Chengdu", "Nanjing", "Foshan"],
  "Colombia": ["Bogotá", "Medellín", "Cali", "Barranquilla", "Cartagena", "Cúcuta", "Bucaramanga", "Pereira", "Santa Marta", "Ibagué"],
  "Costa Rica": ["San José", "Cartago", "Puntarenas", "Limón", "Alajuela"],
  "Croatia": ["Zagreb", "Split", "Rijeka", "Osijek", "Zadar"],
  "Czech Republic": ["Prague", "Brno", "Ostrava", "Plzen", "Liberec"],
  "Denmark": ["Copenhagen", "Aarhus", "Odense", "Aalborg", "Esbjerg"],
  "Dominican Republic": ["Santo Domingo", "Santiago", "La Romana", "San Pedro de Macorís", "Puerto Plata"],
  "Ecuador": ["Quito", "Guayaquil", "Cuenca", "Santo Domingo", "Machala"],
  "Egypt": ["Cairo", "Alexandria", "Giza", "Shubra El-Kheima", "Port Said"],
  "Estonia": ["Tallinn", "Tartu", "Narva", "Pärnu", "Kohtla-Järve"],
  "Finland": ["Helsinki", "Espoo", "Tampere", "Vantaa", "Oulu"],
  "France": ["Paris", "Marseille", "Lyon", "Toulouse", "Nice", "Nantes", "Strasbourg", "Montpellier", "Bordeaux", "Lille"],
  "Georgia": ["Tbilisi", "Batumi", "Kutaisi", "Rustavi", "Gori"],
  "Germany": ["Berlin", "Hamburg", "Munich", "Cologne", "Frankfurt", "Stuttgart", "Düsseldorf", "Dortmund", "Essen", "Leipzig"],
  "Ghana": ["Accra", "Kumasi", "Tamale", "Takoradi", "Cape Coast"],
  "Greece": ["Athens", "Thessaloniki", "Patras", "Heraklion", "Larissa"],
  "Guatemala": ["Guatemala City", "Mixco", "Villa Nueva", "Petapa", "Quetzaltenango"],
  "Honduras": ["Tegucigalpa", "San Pedro Sula", "Choloma", "La Ceiba", "El Progreso"],
  "Hungary": ["Budapest", "Debrecen", "Szeged", "Miskolc", "Pécs"],
  "Iceland": ["Reykjavik", "Kópavogur", "Hafnarfjörður", "Akureyri", "Reykjanesbær"],
  "India": ["Mumbai", "Delhi", "Bangalore", "Hyderabad", "Ahmedabad", "Chennai", "Kolkata", "Surat", "Pune", "Jaipur"],
  "Indonesia": ["Jakarta", "Surabaya", "Bandung", "Bekasi", "Medan"],
  "Iran": ["Tehran", "Mashhad", "Isfahan", "Karaj", "Shiraz"],
  "Iraq": ["Baghdad", "Basra", "Mosul", "Erbil", "Najaf"],
  "Ireland": ["Dublin", "Cork", "Limerick", "Galway", "Waterford"],
  "Israel": ["Jerusalem", "Tel Aviv", "Haifa", "Rishon LeZion", "Petah Tikva"],
  "Italy": ["Rome", "Milan", "Naples", "Turin", "Palermo", "Genoa", "Bologna", "Florence", "Bari", "Catania"],
  "Jamaica": ["Kingston", "Spanish Town", "Portmore", "Montego Bay", "May Pen"],
  "Japan": ["Tokyo", "Yokohama", "Osaka", "Nagoya", "Sapporo", "Fukuoka", "Kobe", "Kawasaki", "Kyoto", "Saitama"],
  "Jordan": ["Amman", "Zarqa", "Irbid", "Russeifa", "Wadi as-Sir"],
  "Kazakhstan": ["Almaty", "Nur-Sultan", "Shymkent", "Aktobe", "Taraz"],
  "Kenya": ["Nairobi", "Mombasa", "Nakuru", "Eldoret", "Kisumu"],
  "Kuwait": ["Kuwait City", "Al Ahmadi", "Hawalli", "As Salimiyah", "Sabah as Salim"],
  "Latvia": ["Riga", "Daugavpils", "Liepāja", "Jelgava", "Jūrmala"],
  "Lebanon": ["Beirut", "Tripoli", "Sidon", "Tyre", "Nabatieh"],
  "Lithuania": ["Vilnius", "Kaunas", "Klaipėda", "Šiauliai", "Panevėžys"],
  "Luxembourg": ["Luxembourg City", "Esch-sur-Alzette", "Differdange", "Dudelange", "Ettelbruck"],
  "Malaysia": ["Kuala Lumpur", "George Town", "Ipoh", "Shah Alam", "Petaling Jaya"],
  "Mexico": ["Ciudad de México", "Guadalajara", "Monterrey", "Puebla", "Tijuana", "León", "Juárez", "Torreón", "Querétaro", "San Luis Potosí"],
  "Morocco": ["Casablanca", "Rabat", "Fez", "Marrakech", "Agadir"],
  "Netherlands": ["Amsterdam", "Rotterdam", "The Hague", "Utrecht", "Eindhoven"],
  "New Zealand": ["Auckland", "Wellington", "Christchurch", "Hamilton", "Tauranga"],
  "Nicaragua": ["Managua", "León", "Masaya", "Matagalpa", "Chinandega"],
  "Nigeria": ["Lagos", "Kano", "Ibadan", "Abuja", "Port Harcourt"],
  "Norway": ["Oslo", "Bergen", "Stavanger", "Trondheim", "Drammen"],
  "Pakistan": ["Karachi", "Lahore", "Faisalabad", "Rawalpindi", "Multan"],
  "Panama": ["Panama City", "San Miguelito", "Tocumen", "David", "Arraiján"],
  "Paraguay": ["Asunción", "Ciudad del Este", "San Lorenzo", "Luque", "Capiatá"],
  "Peru": ["Lima", "Arequipa", "Trujillo", "Chiclayo", "Huancayo", "Piura", "Iquitos", "Cusco", "Chimbote", "Tacna"],
  "Philippines": ["Manila", "Quezon City", "Caloocan", "Davao", "Cebu City"],
  "Poland": ["Warsaw", "Kraków", "Łódź", "Wrocław", "Poznań"],
  "Portugal": ["Lisbon", "Porto", "Vila Nova de Gaia", "Amadora", "Braga"],
  "Qatar": ["Doha", "Al Rayyan", "Umm Salal", "Al Wakrah", "Al Khor"],
  "Romania": ["Bucharest", "Cluj-Napoca", "Timișoara", "Iași", "Constanța"],
  "Russia": ["Moscow", "Saint Petersburg", "Novosibirsk", "Yekaterinburg", "Nizhny Novgorod", "Kazan", "Chelyabinsk", "Omsk", "Samara", "Rostov-on-Don"],
  "Saudi Arabia": ["Riyadh", "Jeddah", "Mecca", "Medina", "Dammam"],
  "Serbia": ["Belgrade", "Novi Sad", "Niš", "Kragujevac", "Subotica"],
  "Singapore": ["Singapore"],
  "Slovakia": ["Bratislava", "Košice", "Prešov", "Žilina", "Banská Bystrica"],
  "Slovenia": ["Ljubljana", "Maribor", "Celje", "Kranj", "Velenje"],
  "South Africa": ["Cape Town", "Johannesburg", "Durban", "Pretoria", "Port Elizabeth"],
  "South Korea": ["Seoul", "Busan", "Incheon", "Daegu", "Daejeon", "Gwangju", "Suwon", "Ulsan", "Changwon", "Goyang"],
  "Spain": ["Madrid", "Barcelona", "Valencia", "Sevilla", "Zaragoza", "Málaga", "Murcia", "Palma", "Las Palmas", "Bilbao"],
  "Sweden": ["Stockholm", "Gothenburg", "Malmö", "Uppsala", "Västerås"],
  "Switzerland": ["Zurich", "Geneva", "Basel", "Lausanne", "Bern"],
  "Thailand": ["Bangkok", "Nonthaburi", "Pak Kret", "Hat Yai", "Chiang Mai"],
  "Turkey": ["Istanbul", "Ankara", "Izmir", "Bursa", "Adana"],
  "Ukraine": ["Kyiv", "Kharkiv", "Odesa", "Dnipro", "Donetsk"],
  "United Arab Emirates": ["Dubai", "Abu Dhabi", "Sharjah", "Al Ain", "Ajman"],
  "United Kingdom": ["London", "Birmingham", "Manchester", "Glasgow", "Liverpool", "Leeds", "Sheffield", "Edinburgh", "Bristol", "Cardiff"],
  "United States": ["New York", "Los Angeles", "Chicago", "Houston", "Phoenix", "Philadelphia", "San Antonio", "San Diego", "Dallas", "San Jose"],
  "Uruguay": ["Montevideo", "Salto", "Paysandú", "Las Piedras", "Rivera"],
  "Venezuela": ["Caracas", "Maracaibo", "Valencia", "Barquisimeto", "Maracay"],
  "Vietnam": ["Ho Chi Minh City", "Hanoi", "Haiphong", "Da Nang", "Bien Hoa"]
}